{"Exp":1500,"UpExp":2520,"Gold":686,"Essence":0,"MapId":0,"LastCityId":0,"Power":0,"EquipPanel":{"5":{"Position":5,"SkillRune":{"SkillId":2001,"Name":"火球术-多重","Des":"增加火球的一个攻击目标","Type":3,"Incre":1,"SuitId":0},"ID":10005,"Name":"新手戒指","Des":"","Type":0,"Level":0,"Gold":10,"AttrList":{"2":5},"skillList":null},"4":{"Position":4,"SkillRune":{"SkillId":2001,"Name":"火球术-多重","Des":"增加火球的一个攻击目标","Type":3,"Incre":1,"SuitId":0},"ID":10004,"Name":"新手头盔","Des":"","Type":0,"Level":0,"Gold":10,"AttrList":{"1":20,"5":3},"skillList":null},"6":{"Position":6,"SkillRune":{"SkillId":2001,"Name":"火球术-多重","Des":"增加火球的一个攻击目标","Type":3,"Incre":1,"SuitId":0},"ID":10006,"Name":"新手手镯","Des":"","Type":0,"Level":0,"Gold":10,"AttrList":{"1":20,"5":3},"skillList":null},"2":{"Position":2,"SkillRune":{"SkillId":2001,"Name":"火球术-多重","Des":"增加火球的一个攻击目标","Type":3,"Incre":1,"SuitId":0},"ID":10002,"Name":"新手衣","Des":"","Type":0,"Level":0,"Gold":30,"AttrList":{"1":50,"5":10},"skillList":null}},"Bags":[{"Position":5,"SkillRune":{"SkillId":2001,"Name":"火球术-多重","Des":"增加火球的一个攻击目标","Type":3,"Incre":1,"SuitId":0},"ID":10005,"Name":"新手戒指","Des":"","Type":0,"Level":0,"Gold":10,"AttrList":{"2":5},"skillList":null},{"Position":4,"SkillRune":{"SkillId":2001,"Name":"火球术-多重","Des":"增加火球的一个攻击目标","Type":3,"Incre":1,"SuitId":0},"ID":10004,"Name":"新手头盔","Des":"","Type":0,"Level":0,"Gold":10,"AttrList":{"1":20,"5":3},"skillList":null},{"Position":6,"SkillRune":{"SkillId":2001,"Name":"火球术-多重","Des":"增加火球的一个攻击目标","Type":3,"Incre":1,"SuitId":0},"ID":10006,"Name":"新手手镯","Des":"","Type":0,"Level":0,"Gold":10,"AttrList":{"1":20,"5":3},"skillList":null},{"Position":2,"SkillRune":{"SkillId":2001,"Name":"火球术-多重","Des":"增加火球的一个攻击目标","Type":3,"Incre":1,"SuitId":0},"ID":10002,"Name":"新手衣","Des":"","Type":0,"Level":0,"Gold":30,"AttrList":{"1":50,"5":10},"skillList":null}],"LastOut":0,"ID":0,"Name":"传奇","Level":6,"HP":248,"SkillIdList":{"1":1001,"2":2001,"3":3001},"IsSurvice":true}